Dxr_Chat/ChatGPT.py
Dxr_Chat/__init__.py
Dxr_Chat/utils.py
Dxr_Crypto/dxr_crypto.py
Dxr_Crypto/QuantumUKey/test0
Dxr_Crypto/QuantumUKey/Files/test0_QuantumApp_check.bin
Dxr_Crypto/QuantumUKey/Files/test0_QuantumApp_config
Dxr_Crypto/QuantumUKey/Files/test0_QuantumApp_fillkey.bin
Dxr_Crypto/lib/linux/libSKF_ms_x86_64.so
Dxr_Crypto/lib/linux/libSKF_sd_x86_64.so
Dxr_Crypto/lib/linux/libSecureCard.so
Dxr_Crypto/lib/linux/libSecureUKey.so
Dxr_Crypto/lib/linux/libes_3000gm.so
Dxr_Crypto/lib/linux/libqcf.so
Dxr_Crypto/lib/linux/libsdsimkey64.so
Dxr_Crypto/lib/linux/libsecudisk_x86_64.so
Dxr_Crypto/lib/linux/libskf_quantum.so
Dxr_Crypto/lib/linux/libtsdkTest_linux.so
Dxr_Crypto/lib/windows/x64/SKF_secom.dll
Dxr_Crypto/lib/windows/x64/SKF_secom.lib
Dxr_Crypto/lib/windows/x64/SKF_usb.dll
Dxr_Crypto/lib/windows/x64/SKF_usb.lib
Dxr_Crypto/lib/windows/x64/SdCryptoStor.dll
Dxr_Crypto/lib/windows/x64/SdCryptoStor.lib
Dxr_Crypto/lib/windows/x64/SecuUKey.dll
Dxr_Crypto/lib/windows/x64/SecuUKey.lib
Dxr_Crypto/lib/windows/x64/SecureCard.dll
Dxr_Crypto/lib/windows/x64/SecureUKey.dll
Dxr_Crypto/lib/windows/x64/SecureUKey.lib
Dxr_Crypto/lib/windows/x64/ShuttleCsp11_3000GM.dll
Dxr_Crypto/lib/windows/x64/ShuttleCsp11_3000GM.lib
Dxr_Crypto/lib/windows/x64/libcrypto.a
Dxr_Crypto/lib/windows/x64/libcrypto.dll
Dxr_Crypto/lib/windows/x64/libcurl.a
Dxr_Crypto/lib/windows/x64/libcurl.dll
Dxr_Crypto/lib/windows/x64/libcurl.lib
Dxr_Crypto/lib/windows/x64/libqcf.dll
Dxr_Crypto/lib/windows/x64/libqcf.lib
Dxr_Crypto/lib/windows/x64/libskf_quantum.dll
Dxr_Crypto/lib/windows/x64/libskf_quantum.lib
Dxr_Crypto/lib/windows/x64/libssl.a
Dxr_Crypto/lib/windows/x64/libssl.dll
Dxr_Crypto/lib/windows/x64/msskf.dll
Dxr_Crypto/lib/windows/x64/msvcr100.dll
Dxr_Crypto/lib/windows/x64/pthreadGC2.dll
Dxr_Crypto/lib/windows/x64/pthreadVC2.dll
Dxr_Crypto/lib/windows/x64/swsoft_engine.dll
Dxr_Crypto/lib/windows/x64/tsdkTest.dll
Dxr_Crypto/lib/windows/x86/SKF_secom.dll
Dxr_Crypto/lib/windows/x86/SKF_usb.dll
dxr-2.1.10.dist-info/METADATA
dxr-2.1.10.dist-info/WHEEL
dxr-2.1.10.dist-info/entry_points.txt
dxr-2.1.10.dist-info/top_level.txt
dxr-2.1.10.dist-info/RECORD
