Metadata-Version: 2.1
Name: DXR
Version: 2.1.10
Summary: DXR is a python library for DXR_mqtt
Home-page: http://pycn.me
Author: luzhipeng
Author-email: 402087139@qq.com
License: MIT
Requires-Dist: paho-mqtt
Requires-Dist: pyyaml
Requires-Dist: pyserial
Requires-Dist: loguru
Requires-Dist: tabulate
Requires-Dist: pymysql
Requires-Dist: sqlalchemy
Requires-Dist: oss2
Requires-Dist: imagezmq
Requires-Dist: simplejpeg
Requires-Dist: pexpect
Requires-Dist: aiortsp
Requires-Dist: click
Requires-Dist: tiktoken
Requires-Dist: prompt-toolkit
Requires-Dist: openai
Requires-Dist: rich
Requires-Dist: fastapi
Requires-Dist: uvicorn
Requires-Dist: psutil
